packageTest/__init__.py
packageTest/packageTest.py
pycupas/Pycupas.py
pycupas/__init__.py
pycupas/cupasApiDriver.py
pycupas-1.0.6.dist-info/METADATA
pycupas-1.0.6.dist-info/WHEEL
pycupas-1.0.6.dist-info/top_level.txt
pycupas-1.0.6.dist-info/RECORD
