Metadata-Version: 2.1
Name: pycupas
Version: 1.0.6
Summary: Make your own coupang partners bot easily
Home-page: https://github.com/winterlood
Author: winterlood
Author-email: winterlood@22hours.co.kr
License: MIT
Platform: UNKNOWN
Requires-Python: >=3
